PolibaseDatabaseService/__init__.py
PolibaseDatabaseService/__main__.py
PolibaseDatabaseService/api.py
PolibaseDatabaseService/const.py
PolibaseDatabaseService/service.py
pih_plb_db-1.1.dist-info/METADATA
pih_plb_db-1.1.dist-info/WHEEL
pih_plb_db-1.1.dist-info/entry_points.txt
pih_plb_db-1.1.dist-info/top_level.txt
pih_plb_db-1.1.dist-info/RECORD
