Metadata-Version: 2.1
Name: pih-plb-db
Version: 1.1
Summary: PIH Polibase database api module
Home-page: https://pacifichosp.com/
Author: Nikita Karachentsev
Author-email: it@pacifichosp.com
License: MIT
Requires-Dist: ipih
